README.rst
setup.py
cfwhitelist/__init__.py
cfwhitelist/whitelist.py
cloudflare_tor_whitelister.egg-info/PKG-INFO
cloudflare_tor_whitelister.egg-info/SOURCES.txt
cloudflare_tor_whitelister.egg-info/dependency_links.txt
cloudflare_tor_whitelister.egg-info/entry_points.txt
cloudflare_tor_whitelister.egg-info/requires.txt
cloudflare_tor_whitelister.egg-info/top_level.txt