Metadata-Version: 1.0
Name: cloudflare-tor-whitelister
Version: 0.1.1
Summary: Cloudflare Whitelister allows site owners to explicitly allow Tor users access there site without being impeded by CAPTCHAs 
Home-page: https://github.com/DonnchaC/cloudflare-tor-whitelister
Author: Donncha O'Cearbhail
Author-email: donncha@donncha.is
License: GPLv3
Keywords: tor,cloudflare,firewall
Platform: UNKNOWN
